roma_blackbox/__init__.py
roma_blackbox/attestation.py
roma_blackbox/filters.py
roma_blackbox/metrics.py
roma_blackbox/pii_patterns.py
roma_blackbox/policy.py
roma_blackbox/storage.py
roma_blackbox/wrapper.py
roma_blackbox/integrations/__init__.py
roma_blackbox/integrations/langchain.py
roma_blackbox-0.3.0.dist-info/licenses/LICENSE
roma_blackbox-0.3.0.dist-info/METADATA
roma_blackbox-0.3.0.dist-info/WHEEL
roma_blackbox-0.3.0.dist-info/top_level.txt
roma_blackbox-0.3.0.dist-info/RECORD
