Metadata-Version: 2.4
Name: roma-blackbox
Version: 0.3.0
Summary: Privacy-first monitoring wrapper for ROMA agents
Home-page: https://github.com/your-org/roma-blackbox
Author: Your Name
Author-email: your.email@example.com
Requires-Python: >=3.9
License-File: LICENSE
Requires-Dist: pydantic>=2.0.0
Provides-Extra: postgresql
Requires-Dist: asyncpg>=0.29.0; extra == "postgresql"
Provides-Extra: prometheus
Requires-Dist: prometheus-client>=0.19.0; extra == "prometheus"
Provides-Extra: langchain
Requires-Dist: langchain>=0.1.0; extra == "langchain"
Requires-Dist: langchain-core>=0.1.0; extra == "langchain"
Provides-Extra: all
Requires-Dist: asyncpg>=0.29.0; extra == "all"
Requires-Dist: prometheus-client>=0.19.0; extra == "all"
Requires-Dist: cryptography>=41.0.0; extra == "all"
Requires-Dist: langchain>=0.1.0; extra == "all"
Requires-Dist: langchain-core>=0.1.0; extra == "all"
Provides-Extra: dev
Requires-Dist: pytest>=7.4.0; extra == "dev"
Requires-Dist: pytest-asyncio>=0.21.0; extra == "dev"
Requires-Dist: pytest-cov>=4.1.0; extra == "dev"
Requires-Dist: black>=23.0.0; extra == "dev"
Requires-Dist: ruff>=0.1.0; extra == "dev"
Dynamic: author
Dynamic: author-email
Dynamic: home-page
Dynamic: license-file
Dynamic: requires-python
